setup.py
email/feedparser.py
micropython_email.feedparser.egg-info/PKG-INFO
micropython_email.feedparser.egg-info/SOURCES.txt
micropython_email.feedparser.egg-info/dependency_links.txt
micropython_email.feedparser.egg-info/requires.txt
micropython_email.feedparser.egg-info/top_level.txt